odoo9_addon_l10n_es_irnr-9.0.1.0.0-py2.7-nspkg.pth
odoo9_addon_l10n_es_irnr-9.0.1.0.0.dist-info/DESCRIPTION.rst
odoo9_addon_l10n_es_irnr-9.0.1.0.0.dist-info/METADATA
odoo9_addon_l10n_es_irnr-9.0.1.0.0.dist-info/RECORD
odoo9_addon_l10n_es_irnr-9.0.1.0.0.dist-info/WHEEL
odoo9_addon_l10n_es_irnr-9.0.1.0.0.dist-info/metadata.json
odoo9_addon_l10n_es_irnr-9.0.1.0.0.dist-info/namespace_packages.txt
odoo9_addon_l10n_es_irnr-9.0.1.0.0.dist-info/top_level.txt
odoo_addons/l10n_es_irnr/README.rst
odoo_addons/l10n_es_irnr/__init__.py
odoo_addons/l10n_es_irnr/__openerp__.py
odoo_addons/l10n_es_irnr/data/fiscal_position_taxes_irnr.xml
odoo_addons/l10n_es_irnr/data/fiscal_positions_irnr.xml
odoo_addons/l10n_es_irnr/data/taxes_irnr.xml
odoo_addons/l10n_es_irnr/static/description/icon.png
